django_forge_issues/__init__.py
django_forge_issues/forge.py
django_forge_issues/forms.py
django_forge_issues/urls.py
django_forge_issues/views.py
django_forge_issues-0.2.0.dist-info/METADATA
django_forge_issues-0.2.0.dist-info/WHEEL
django_forge_issues-0.2.0.dist-info/top_level.txt
django_forge_issues-0.2.0.dist-info/RECORD
