Metadata-Version: 2.4
Name: django-forge-issues
Version: 0.2.0
Summary: Create github/gitlab issues from a Django interface
Requires-Python: >=3.13
Requires-Dist: django>=5.2
Requires-Dist: httpx>=0.28.1
